OutLines/__absorption__.py
OutLines/__funcs__.py
OutLines/__init__.py
OutLines/__nebular__.py
OutLines/__params__.py
OutLines/__profiles__.py
OutLines/__properties__.py
OutLines/__resonfluor__.py
OutLines/__visualize__.py
specoutlines-1.0.2.dist-info/licenses/LICENSE
specoutlines-1.0.2.dist-info/METADATA
specoutlines-1.0.2.dist-info/WHEEL
specoutlines-1.0.2.dist-info/top_level.txt
specoutlines-1.0.2.dist-info/RECORD
