Metadata-Version: 2.4
Name: SpecOutLines
Version: 1.0.2
Summary: model spectral line profiles for astrophysical winds, bubbles, and outflows
Author: Sophia Flury
License-Expression: GPL-3.0
Project-URL: Homepage, https://github.com/sflury/OutLines
Project-URL: Issues, https://github.com/sflury/OutLines/issues
Project-URL: Documentation, https://github.com/sflury/OutLines/wiki
Classifier: Programming Language :: Python :: 3
Classifier: Programming Language :: Python :: 3.12
Classifier: Operating System :: OS Independent
Requires-Python: >=3.12.9
License-File: LICENSE
Requires-Dist: numpy>=2.3.5
Requires-Dist: scipy>=1.17.0
Requires-Dist: matplotlib>=3.10.0
Dynamic: license-file
